fastapi_crud/__init__.py
fastapi_crud/config.py
fastapi_crud/fastapicrud.py
fastapi_crud/router.py
fastapi_crud/schema.py
fastapi_crud/session.py
fastapi_crud/type_map.py
fastapi_crud/types.py
fastapi_crud-0.0.3.dist-info/LICENSE
fastapi_crud-0.0.3.dist-info/METADATA
fastapi_crud-0.0.3.dist-info/WHEEL
fastapi_crud-0.0.3.dist-info/top_level.txt
fastapi_crud-0.0.3.dist-info/RECORD
