Metadata-Version: 2.1
Name: fastapi-crud
Version: 0.0.3
Summary: Automatic CRUD route generation from SQLAlchemy models for FastAPI
Home-page: https://github.com/miikapo/fastapi-crud
Author: Miika Potka
Author-email: miikapotka@gmail.com
License: Apache License 2.0
Project-URL: Bug Tracker, https://github.com/miikapo/fastapi-crud/issues
Platform: UNKNOWN
Classifier: Development Status :: 3 - Alpha
Classifier: Programming Language :: Python :: 3
Classifier: License :: OSI Approved :: Apache Software License
Classifier: Operating System :: OS Independent
Requires-Python: >=3.6
License-File: LICENSE
Requires-Dist: fastapi
Requires-Dist: SQLAlchemy[asyncio]
